a003558/__init__.py
a003558/brain.py
a003558/core.py
a003558/cosmos.py
a003558/coupling.py
a003558/export_blender.py
a003558/horizons.py
a003558/number_theory.py
a003558/octahedral_matrix.py
a003558/octonions.py
a003558/viz.py
a003558/viz_octa.py
a003558-0.1.25.dist-info/licenses/LICENSE
a003558-0.1.25.dist-info/METADATA
a003558-0.1.25.dist-info/WHEEL
a003558-0.1.25.dist-info/top_level.txt
a003558-0.1.25.dist-info/RECORD
