Metadata-Version: 2.4
Name: a003558
Version: 0.1.25
Summary: A003558 – universal clock
Author-email: Bram Dhont <bram@example.com>
License: MIT
Project-URL: Homepage, https://github.com/bramdhontsr/A003558-universal-clock
Project-URL: Repository, https://github.com/bramdhontsr/A003558-universal-clock
Requires-Python: >=3.10
License-File: LICENSE
Requires-Dist: numpy>=1.26
Provides-Extra: viz
Requires-Dist: matplotlib; extra == "viz"
Requires-Dist: numpy>=1.26; extra == "viz"
Dynamic: license-file
